niku.py
setup.py
niku.egg-info/PKG-INFO
niku.egg-info/SOURCES.txt
niku.egg-info/dependency_links.txt
niku.egg-info/entry_points.txt
niku.egg-info/top_level.txt