Metadata-Version: 1.0
Name: niku
Version: 1.0
Summary: PID Controller for sous vide
Home-page: https://github.com/hamano/python-niku/
Author: Tsukasa Hamano
Author-email: code@cuspy.org
License: BSD
Platform: UNKNOWN
